pybacktrans/__init__.py
pybacktrans/constants.py
pybacktrans/models.py
pybacktrans/translator.py
pybacktrans-0.1.4.dist-info/LICENSE
pybacktrans-0.1.4.dist-info/METADATA
pybacktrans-0.1.4.dist-info/WHEEL
pybacktrans-0.1.4.dist-info/top_level.txt
pybacktrans-0.1.4.dist-info/RECORD
