Metadata-Version: 2.1
Name: pybacktrans
Version: 0.1.4
Summary: PyBacktrans: Python library for backtranslation
Home-page: https://github.com/monologg/py-backtrans
Author: Jangwon Park
Author-email: adieujw@gmail.com
License: MIT
Platform: UNKNOWN
Classifier: Programming Language :: Python :: 3
Classifier: License :: OSI Approved :: MIT License
Classifier: Operating System :: OS Independent
Requires-Python: >=3
Requires-Dist: googletrans
Requires-Dist: nltk
